setup.py
dsnd_probability_agottani/Binomialdistribution.py
dsnd_probability_agottani/Gaussiandistribution.py
dsnd_probability_agottani/Generaldistribution.py
dsnd_probability_agottani/__init__.py
dsnd_probability_agottani.egg-info/PKG-INFO
dsnd_probability_agottani.egg-info/SOURCES.txt
dsnd_probability_agottani.egg-info/dependency_links.txt
dsnd_probability_agottani.egg-info/not-zip-safe
dsnd_probability_agottani.egg-info/top_level.txt