Metadata-Version: 1.0
Name: dsnd-probability-agottani
Version: 1.5
Summary: Gaussian and Binomial Distributions
Home-page: UNKNOWN
Author: Luis Fernando Rodrigues Agottani
Author-email: luisfernandoengmec@gmail.com
License: UNKNOWN
Platform: UNKNOWN
